valider/__init__.py
valider/base.py
valider/document_validators.py
valider/field_validators.py
valider-0.1.1.dist-info/LICENSE
valider-0.1.1.dist-info/METADATA
valider-0.1.1.dist-info/WHEEL
valider-0.1.1.dist-info/RECORD
