Metadata-Version: 2.3
Name: valider
Version: 0.1.1
Summary: Validation framework for financial document processing
Author: Fin Officer Team
Requires-Python: >=3.8,<4.0
Classifier: Programming Language :: Python :: 3
Classifier: Programming Language :: Python :: 3.8
Classifier: Programming Language :: Python :: 3.9
Classifier: Programming Language :: Python :: 3.10
Classifier: Programming Language :: Python :: 3.11
Classifier: Programming Language :: Python :: 3.12
Classifier: Programming Language :: Python :: 3.13
Requires-Dist: invutil @ file:///home/tom/github/fin-officer/invutil
Requires-Dist: pydantic (>=2.0.0,<3.0.0)
